{
    "MovableWall":
    [
        {
            "x": ,
            "y": ,
            "structure_direction": "right",
            "move_direction": "null",
            "move_distance": ,
            "length": ,
            "speed": ,
            "can_be_affected_by_time_control": true
        }
    ],
    "ReceptorAndEffectors":
    [
        {
            "receptor":
            {
                "type": "pressure_plate",
                "activation_message": "move left 14",
                "release_message": "move right 14",
                "x": ,
                "y": 
            },
            "effector_postal_codes":
            [
               603979776
            ]
        }
    ],
    "NPCs": []
}